sphinxcontrib/stan/__init__.py
tests/test_build.py
tests/test_parsing.py
sphinx_stan-0.1.6.dist-info/METADATA
sphinx_stan-0.1.6.dist-info/WHEEL
sphinx_stan-0.1.6.dist-info/top_level.txt
sphinx_stan-0.1.6.dist-info/RECORD
