Metadata-Version: 2.1
Name: sphinx-stan
Version: 0.1.6
Requires-Dist: sphinx
Provides-Extra: tests
Requires-Dist: flake8 ; extra == 'tests'
Requires-Dist: pytest ; extra == 'tests'
Requires-Dist: pytest-cov ; extra == 'tests'
Requires-Dist: twine ; extra == 'tests'
